dezmq/__init__.py
dezmq/__main__.py
dezmq/dezmq.py
dezmq-0.1.0a1.dist-info/entry_points.txt
dezmq-0.1.0a1.dist-info/LICENSE
dezmq-0.1.0a1.dist-info/WHEEL
dezmq-0.1.0a1.dist-info/METADATA
dezmq-0.1.0a1.dist-info/RECORD
