Metadata-Version: 2.1
Name: dezmq
Version: 0.1.0a1
Summary: dezmq
Home-page: https://github.com/ffreemt/dezbee-zmq
License: MIT
Author: ffreemt
Requires-Python: >=3.8.3,<4.0.0
Classifier: License :: OSI Approved :: MIT License
Classifier: Programming Language :: Python :: 3
Classifier: Programming Language :: Python :: 3.9
Classifier: Programming Language :: Python :: 3.10
Requires-Dist: ezbee (>=0.1.2,<0.2.0)
Requires-Dist: logzero (>=1.7.0,<2.0.0)
Requires-Dist: pyzmq (>=25.0.0b1,<26.0.0)
Requires-Dist: scikit-learn (>=1.1.3,<2.0.0)
Requires-Dist: set-loglevel (>=0.1.2,<0.2.0)
Requires-Dist: typer (>=0.4.1,<0.5.0)
Project-URL: Repository, https://github.com/ffreemt/dezbee-zmq
